furo_tb/__init__.py
furo_tb/topbar.py
furo_tb/theme/page.html
furo_tb/theme/theme.conf
furo_tb/theme/topbar.css
furo_tb/theme/topbar.html
furo_tb-0.0.1.dist-info/entry_points.txt
furo_tb-0.0.1.dist-info/LICENSE
furo_tb-0.0.1.dist-info/WHEEL
furo_tb-0.0.1.dist-info/METADATA
furo_tb-0.0.1.dist-info/RECORD
