Metadata-Version: 2.1
Name: furo_tb
Version: 0.0.1
Summary: Adding a topbar to the furo sphinx theme.
Author-email: Chris Sewell <chrisj_sewell@hotmail.com>
Requires-Python: >=3.7
Classifier: Framework :: Sphinx
Classifier: Framework :: Sphinx :: Theme
Classifier: License :: OSI Approved :: MIT License
Classifier: Environment :: Web Environment
Classifier: Topic :: Documentation
Classifier: Topic :: Software Development :: Documentation
Requires-Dist: furo~=2022.1.2
Requires-Dist: myst-parser ; extra == "docs"
Requires-Dist: pytest ; extra == "testing"
Requires-Dist: beautifulsoup4 ; extra == "testing"
Project-URL: Documentation, https://furo-topbar.readthedocs.io/
Project-URL: Source, https://github.com/chrisjsewell/furo-topbar
Provides-Extra: docs
Provides-Extra: testing
